{
  "products": [
    {
      "id": 10001,
      "name": "Apple iPhone 15",
      "overview": "Premium Apple smartphone with A16 Bionic chip and dynamic island display.",
      "long_description": "The iPhone 15 features Apple's powerful A16 Bionic processor, a stunning Super Retina XDR display, and an improved dual-camera system with enhanced low-light performance. It offers smooth performance, long battery life, and a sleek design with USB-C support.",
      "price": 79900,
      "poster": "/assets/images/iphone15.png",
      "image_local": "/assets/images/10001.avif",
      "rating": 5,
      "in_stock": true,
      "size": 20,
      "best_seller": true
    },
    {
      "id": 10002,
      "name": "Samsung Galaxy S24",
      "overview": "Flagship Samsung phone with AI features and powerful Snapdragon processor.",
      "long_description": "The Samsung Galaxy S24 comes with advanced AI capabilities, a high-performance Snapdragon processor, and a stunning AMOLED display. It delivers excellent camera quality, long battery life, and premium design suitable for everyday and professional use.",
      "price": 74999,
      "poster": "/assets/images/s24.png",
      "image_local": "/assets/images/10002.avif",
      "rating": 5,
      "in_stock": true,
      "size": 15,
      "best_seller": true
    },
    {
      "id": 10003,
      "name": "OnePlus 12",
      "overview": "High-performance flagship with fast charging and smooth UI.",
      "long_description": "OnePlus 12 features the Snapdragon 8 Gen 3 chipset, ultra-fast charging, and a fluid AMOLED display with high refresh rate. It offers a clean OxygenOS experience, strong battery backup, and a premium camera setup.",
      "price": 64999,
      "poster": "/assets/images/never.png",
      "image_local": "/assets/images/10003.avif",
      "rating": 5,
      "in_stock": true,
      "size": 15,
      "best_seller": true
    },
    {
      "id": 10004,
      "name": "Xiaomi 14",
      "overview": "Compact flagship with Leica-powered camera system.",
      "long_description": "Xiaomi 14 offers a powerful Snapdragon chipset and a Leica-tuned camera system for professional-grade photography. It features a premium design, fast charging, and a vibrant AMOLED display.",
      "price": 69999,
      "poster": "/assets/images/xiami-14.png",
      "image_local": "/assets/images/10004.avif",
      "rating": 4,
      "in_stock": true,
      "size": 15,
      "best_seller": false
    },
    {
      "id": 10005,
      "name": "Realme GT 6",
      "overview": "Performance-focused phone with stylish design and fast charging.",
      "long_description": "Realme GT 6 delivers high-speed performance with a powerful processor, fast charging capabilities, and a modern design. It is ideal for gamers and heavy users looking for value.",
      "price": 35999,
      "poster": "assets/images/realme-gt6.png",
      "image_local": "/assets/images/10005.avif",
      "rating": 4,
      "in_stock": true,
      "size": 15,
      "best_seller": true
    },
    {
      "id": 10006,
      "name": "iQOO Neo 9 Pro",
      "overview": "Gaming-focused smartphone with flagship-level performance.",
      "long_description": "The iQOO Neo 9 Pro is designed for gamers, featuring a powerful processor, advanced cooling system, and ultra-smooth display. It ensures high frame rates and long gaming sessions without overheating.",
      "price": 37999,
      "poster": "/assets/images/iQOO.png",
      "image_local": "/assets/images/10006.avif",
      "rating": 5,
      "in_stock": true,
      "size": 15,
      "best_seller": true
    },
    {
      "id": 10010,
      "name": "Nothing Phone (2)",
      "overview": "Unique design phone with glyph interface flagship-level performance.",
      "long_description": "Nothing Phone (2) stands out with its transparent design and glyph lighting system. It offers a clean Android experience, solid performance, and good cameras.",
      "price": 44999,
      "poster": "/assets/images/noting.png",
      "image_local": "/assets/images/10010.avif",
      "rating": 4,
      "in_stock": true,
      "size": 15,
      "best_seller": true
    },
    {
      "id": 10011,
      "name": "Google Pixel 8",
      "overview": "AI-powered smartphone with best-in-class camera flagship-level performance.",
      "long_description": "Pixel 8 delivers exceptional photography using Google's AI algorithms. It offers a clean Android experience, strong security updates, and reliable performance.",
      "price": 75999,
      "poster": "/assets/images/google.png",
      "image_local": "/assets/images/10011.avif",
      "rating": 5,
      "in_stock": true,
      "size": 20,
      "best_seller": true
    },
    {
      "id": 10020,
      "name": "Infinix Zero 30",
      "overview": "Affordable phone with strong camera features flagship-level performance.",
      "long_description": "Infinix Zero 30 offers a high-resolution camera, stylish design, and decent performance at a budget price, making it a good value-for-money device.",
      "price": 22999,
      "poster": "/assets/images/Infinix.png",
      "image_local": "/assets/images/10020.avif",
      "rating": 3,
      "in_stock": true,
      "size": 20,
      "best_seller": false
    }
  ],
  "featured_products": [
    {
      "id": 10002,
      "name": "Samsung Galaxy S24",
      "overview": "Flagship Samsung phone with AI features and powerful Snapdragon processor.",
      "long_description": "The Samsung Galaxy S24 comes with advanced AI capabilities, a high-performance Snapdragon processor, and a stunning AMOLED display. It delivers excellent camera quality, long battery life, and premium design suitable for everyday and professional use.",
      "price": 74999,
      "poster": "/assets/images/s24.png",
      "image_local": "/assets/images/10002.avif",
      "rating": 5,
      "in_stock": true,
      "size": 15,
      "best_seller": true
    },
    {
      "id": 10003,
      "name": "OnePlus 12",
      "overview": "High-performance flagship with fast charging and smooth UI.",
      "long_description": "OnePlus 12 features the Snapdragon 8 Gen 3 chipset, ultra-fast charging, and a fluid AMOLED display with high refresh rate. It offers a clean OxygenOS experience, strong battery backup, and a premium camera setup.",
      "price": 64999,
      "poster": "/assets/images/never.png",
      "image_local": "/assets/images/10003.avif",
      "rating": 5,
      "in_stock": true,
      "size": 15,
      "best_seller": true
    },
    {
      "id": 10011,
      "name": "Google Pixel 8",
      "overview": "AI-powered smartphone with best-in-class camera.",
      "long_description": "Pixel 8 delivers exceptional photography using Google's AI algorithms. It offers a clean Android experience, strong security updates, and reliable performance.",
      "price": 75999,
      "poster": "/assets/images/google.png",
      "image_local": "/assets/images/10011.avif",
      "rating": 5,
      "in_stock": true,
      "size": 20,
      "best_seller": true
    }
  ],
  "orders": [
    {
      "cartList": [
        {
          "id": 10002,
          "name": "Samsung Galaxy S24",
          "overview": "Flagship Samsung phone with AI features and powerful Snapdragon processor.",
          "long_description": "The Samsung Galaxy S24 comes with advanced AI capabilities, a high-performance Snapdragon processor, and a stunning AMOLED display. It delivers excellent camera quality, long battery life, and premium design suitable for everyday and professional use.",
          "price": 74999,
          "poster": "/assets/images/s24.png",
          "image_local": "/assets/images/10002.avif",
          "rating": 5,
          "in_stock": true,
          "size": 15,
          "best_seller": true
        }
      ],
      "amount_Paid": 74999,
      "quantity": 1,
      "user": {},
      "id": 1
    }
  ],
  "users": [
    {
      "email": "jaswanth@gmail.com",
      "password": "$2a$10$A7np3PBgce0lGWHg8c6HMuWb20wuTAlS8Jxczoy/qOvKvYFZ3BkKW",
      "name": "jaswanth",
      "id": 1
    }
  ]
}